cracknuts_squirrel/__init__.py
cracknuts_squirrel/cpa_analysis.py
cracknuts_squirrel/preprocessingBasic.py
cracknuts_squirrel/staticalgin.py
cracknuts_squirrel/traceIO.py
cracknuts_squirrel-0.1.0a1.dist-info/licenses/LICENSE
cracknuts_squirrel-0.1.0a1.dist-info/METADATA
cracknuts_squirrel-0.1.0a1.dist-info/WHEEL
cracknuts_squirrel-0.1.0a1.dist-info/top_level.txt
cracknuts_squirrel-0.1.0a1.dist-info/RECORD
